MIPS32/mips32.v
//This module contains behavioral description verilog code
//for 5-stage pipelined MIPS32 RISC processor. 1-Bit regis-
//ster is used to halt processor(HALTD). 1-Bit register is
//used to evaluate branch conditions(TAKEN_BRANCH) and pre-
//vent any state changes.

module pipe_mips32(clk1,clk2);
  //Port declartion for module. Two-phased clock
  input clk1,clk2;

  //Registers for each stage  in pipeline process
  reg [31:0]PC,IF_ID_IR,IF_ID_NPC;
  reg [31:0]ID_EX_IR,ID_EX_NPC,ID_EX_A,ID_EX_B,ID_EX_Mem;
  reg [2:0]ID_EX_Type,EX_Mem_Type,Mem_WB_Type;
  reg [31:0]EX_Mem_IR,EX_Mem_ALUOut,EX_Mem_B;
  reg       EX_Mem_cond;
  reg [31:0]Mem_WB_IR,Mem_WB_ALUOut,Mem_WB_LMD;

  //Register bank(32x32) and 1024x32 memory
  reg [31:0]Reg[0:31];
  reg [31:0]Mem[0:1023];

  //ALU Instructions as parameters
  parameter ADD=6'b000000,SUB=6'b000001,AND=6'b000010,
            OR=6'b000011,SLT=6'b000100,MUL=6'b000101,
            HLT=6'b111111,LW=6'b001000,SW=6'b001001,
            ADDI=6'b001010,SUBI=6'b001011,SLTI=6'b001100,
            BNEQZ=6'b001101,BEQZ=6'b001110;
  //Special instructions as parameters
  parameter RR_ALU=3'b000,RM_ALU=3'b001,LOAD=3'b001,
            STORE=3'b011,BRANCH=3'b100,HALT=3'b101;

  //1-Bit flag for halting instructions
  reg HALTED;

  //1-Bit flag for branch instructions
  reg TAKEN_BRANCH;

  //Instruction Fetch Stage
  always@(posedge clk1)
  if(HALTED==0)
  begin
    if(((EX_Mem_IR[31:26]==BEQZ) && (EX_Mem_cond==1)) ||
        ((EX_Mem_IR[31:26]==BNEQZ) && (EX_Mem_cond==0)))
    begin
      IF_ID_IR <= #2 Mem[EX_Mem_ALUOut];
      TAKEN_BRANCH <= #2 1'b1;
      IF_ID_NPC <= #2 EX_Mem_ALUOut+1;
      PC <= #2 EX_Mem_ALUOut+1;
    end
    else
    begin
      IF_ID_IR <= #2 Mem[PC];
      IF_ID_NPC <= #2 PC+1;
      PC <= #2 PC+1;
    end
  end

  //Instruction Decode stage
  always@(posedge clk2)
  if(HALTED==0)
  begin
    //rs value from instruction
    if(IF_ID_IR[25:21]==5'b00000)
      ID_EX_A <= 0;
    else
      ID_EX_A <= #2 Reg[IF_ID_IR[25:21]];

    //rt value from instruction
    if(IF_ID_IR[20:16]==5'b00000)
      ID_EX_B <=0;
    else
      ID_EX_B <= #2 Reg[IF_ID_IR[20:16]];

    //forwarding remaining instructions
    ID_EX_NPC <= #2 IF_ID_NPC;
    ID_EX_IR <= #2 IF_ID_IR;
    ID_EX_Mem <= #2 {{16{IF_ID_IR[15]}},{IF_ID_IR[15:0]}};

    //Setting the execution command type
    case(IF_ID_IR[31:26])
      ADD,SUB,AND,OR,SLT,MUL: ID_EX_Type <= #2 RR_ALU;
      ADDI,SUBI,SLTI:         ID_EX_Type <= #2 RM_ALU;
      LW:                     ID_EX_Type <= #2 LOAD;
      SW:                     ID_EX_Type <= #2 STORE;
      BNEQZ,BEQZ:             ID_EX_Type <= #2 BRANCH;
      HLT:                    ID_EX_Type <= #2 HALT;
      default:                ID_EX_Type <= #2 HALT;
    endcase
  end

  //Execution stage
  always@(posedge clk1)
  if(HALTED==0)
  begin
    EX_Mem_Type <= #2 ID_EX_Type;
    EX_Mem_IR <= #2 ID_EX_Type;
    TAKEN_BRANCH <= #2 0;

    case(ID_EX_Type)
      //Register to Register type of instruction
      RR_ALU: begin
                case(ID_EX_IR[31:26])
                  ADD: EX_Mem_ALUOut <= #2 ID_EX_A + ID_EX_B;
                  SUB: EX_Mem_ALUOut <= #2 ID_EX_A - ID_EX_B;
                  MUL: EX_Mem_ALUOut <= #2 ID_EX_A * ID_EX_B;
                  AND: EX_Mem_ALUOut <= #2 ID_EX_A & ID_EX_B;
                  OR:  EX_Mem_ALUOut <= #2 ID_EX_A | ID_EX_B;
                  SLT: EX_Mem_ALUOut <= #2 ID_EX_A < ID_EX_B;
                  default: EX_Mem_ALUOut <= #2 32'hxxxxxxxx;
                endcase
              end

      //Register to Memory type of instruction
      RM_ALU: begin
                case(ID_EX_IR[31:26])
                  ADDI: EX_Mem_ALUOut <= #2 ID_EX_A + ID_EX_Mem;
                  SUBI: EX_Mem_ALUOut <= #2 ID_EX_A - ID_EX_Mem;
                  SLTI: EX_Mem_ALUOut <= #2 ID_EX_A < ID_EX_Mem;
                  default: EX_Mem_ALUOut <= #2 32'hxxxxxxxx;
                endcase
              end

      LOAD,STORE:
              begin
                EX_Mem_ALUOut <= #2 ID_EX_A + ID_EX_Mem;
                EX_Mem_B <= #2 ID_EX_B;
              end

      BRANCH: begin
                EX_Mem_ALUOut <= #2 ID_EX_NPC + ID_EX_Mem;
                EX_Mem_cond <= #2 (ID_EX_A==0);
              end
    endcase
  end  

  //Memory Access stage
  always@(posedge clk2)
  if(HALTED==0)
  begin
    Mem_WB_Type <= #2 EX_Mem_Type;
    Mem_WB_IR <= #2 EX_Mem_IR;

    //Memory access based on type of instruction
    case(EX_Mem_Type)
      RR_ALU,RM_ALU: Mem_WB_ALUOut <= #2 EX_Mem_ALUOut;
      LOAD: Mem_WB_ALUOut <= #2 Mem[EX_Mem_ALUOut];
      STORE: if(TAKEN_BRANCH==0)
               Mem[EX_Mem_ALUOut] <= #2 EX_Mem_B;
    endcase
  end

  //Write Back stage
  always@(posedge clk1)
  begin
    if(TAKEN_BRANCH==0)
    case(Mem_WB_Type)
      RR_ALU: Reg[Mem_WB_IR[15:11]] <= #2 Mem_WB_ALUOut;
      RM_ALU: Reg[Mem_WB_IR[20:16]] <= #2 Mem_WB_ALUOut;
      LOAD: Reg[Mem_WB_IR[20:16]] <= #2 Mem_WB_LMD;
      HALT: HALTED <= #2 1'b1;
    endcase
  end
endmodule

MIPS32/addnumbers_tb.v
//This testbench adds three numbers from r1,r2,r3 registers
//and stores them in r4 register. The assembly language pr-
//ogram is as below which is then converted to machine lan-
//gugage code in our test bench.
//Assembly laguage program
//#########################################################
//ADDI R1,R0,10
//ADDI R2,R0,20
//ADDI R3,R0,25
//ADD R4,R1,R2
//ADD R5,R4,R3
//HLT
//#########################################################

module addertest_mips32;
  reg clk1,clk2;
  integer k;
  pipe_mips32 add(.clk1(clk1),.clk2(clk2));

  //Procedural block to instantiate clocks;
  initial
  begin
    clk1=0;clk2=0;
    repeat(50)
    begin
      #5 clk1=1;#5 clk1=0;
      #5 clk2=1;#5 clk2=0;
    end
  end

  //Machine code for above assembly language
  initial
  begin
    add.HALTED=0;
    add.PC=0;
    add.TAKEN_BRANCH=0;

    for(k=0;k<31;k=k+1)
      add.Reg[k]=k;
    //ADDI R1,R0,10
    add.Mem[0]=32'h2801000a;
    //ADDI R2,R0,20
    add.Mem[1]=32'h28020014;
    //ADDI R3,R0,25
    add.Mem[2]=32'h28030019;
    //dummy OR instruction for pipeline to advance
    add.Mem[3]=32'h0ce77800;
    //dummy OR instruction for pipeline to advance
    add.Mem[4]=32'h0ce77800;
    //ADD R4,R1,R2
    add.Mem[5]=32'h00222000;
    //dummy OR instruction for pipeline to advance
    add.Mem[6]=32'h0ce77800;
    //ADD R5,R4,R3;
    add.Mem[7]=32'h00832800;
    //HLT
    add.Mem[8]=32'hfc000000;

    #700
    for(k=0;k<6;k=k+1)
      $display("R%1d - %2d",k,add.Reg[k]);
  end

  //vcd file generation
  initial
  begin
    $dumpfile("adder.vcd");
    $dumpvars(0,addertest_mips32);
    #1000 $finish;
  end
endmodule

MIPS32/adder.vcd
$date
	Mon Jul 10 06:15:56 2023
$end

$version
	Synopsys VCS version Q-2020.03-SP1-1_Full64
$end

$timescale
	1s
$end

$comment Csum: 1 0662507d5483dff3 $end


$scope module addertest_mips32 $end
$var reg 1 ! clk1 $end
$var reg 1 " clk2 $end
$var integer 32 # k $end

$scope module add $end
$var reg 32 $ PC [31:0] $end
$var reg 1 % HALTED $end
$var reg 1 & TAKEN_BRANCH $end
$var wire 1 ! clk1 $end
$var wire 1 " clk2 $end
$var reg 32 ' IF_ID_IR [31:0] $end
$var reg 32 ( IF_ID_NPC [31:0] $end
$var reg 32 ) ID_EX_IR [31:0] $end
$var reg 32 * ID_EX_NPC [31:0] $end
$var reg 32 + ID_EX_A [31:0] $end
$var reg 32 , ID_EX_B [31:0] $end
$var reg 32 - ID_EX_Mem [31:0] $end
$var reg 3 . ID_EX_Type [2:0] $end
$var reg 3 / EX_Mem_Type [2:0] $end
$var reg 3 0 Mem_WB_Type [2:0] $end
$var reg 32 1 EX_Mem_IR [31:0] $end
$var reg 32 2 EX_Mem_ALUOut [31:0] $end
$var reg 32 3 EX_Mem_B [31:0] $end
$var reg 1 4 EX_Mem_cond $end
$var reg 32 5 Mem_WB_IR [31:0] $end
$var reg 32 6 Mem_WB_ALUOut [31:0] $end
$var reg 32 7 Mem_WB_LMD [31:0] $end
$upscope $end

$upscope $end

$enddefinitions $end

#0
$dumpvars
x4
0%
0&
0!
0"
bxxxxxxxxxxxxxxxxxxxxxxxxxxxxxxxx 2
bxxxxxxxxxxxxxxxxxxxxxxxxxxxxxxxx 3
bxxxxxxxxxxxxxxxxxxxxxxxxxxxxxxxx 1
bxxx /
bxxxxxxxxxxxxxxxxxxxxxxxxxxxxxxxx +
bxxxxxxxxxxxxxxxxxxxxxxxxxxxxxxxx ,
bxxxxxxxxxxxxxxxxxxxxxxxxxxxxxxxx )
bxxxxxxxxxxxxxxxxxxxxxxxxxxxxxxxx -
bxxxxxxxxxxxxxxxxxxxxxxxxxxxxxxxx *
bxxx .
bxxxxxxxxxxxxxxxxxxxxxxxxxxxxxxxx '
bxxxxxxxxxxxxxxxxxxxxxxxxxxxxxxxx (
bxxxxxxxxxxxxxxxxxxxxxxxxxxxxxxxx 6
bxxxxxxxxxxxxxxxxxxxxxxxxxxxxxxxx 5
bxxx 0
b00000000000000000000000000000000 $
b00000000000000000000000000011111 #
bxxxxxxxxxxxxxxxxxxxxxxxxxxxxxxxx 7
$end
#5
1!
#7
b00101000000000010000000000001010 '
b00000000000000000000000000000001 (
b00000000000000000000000000000001 $
#10
0!
#15
1"
b00000000000000000000000000000000 +
#17
b00000000000000000000000000000001 ,
b00000000000000000000000000000001 *
b00101000000000010000000000001010 )
b00000000000000000000000000001010 -
b001 .
#20
0"
#25
1!
#27
b00101000000000100000000000010100 '
b00000000000000000000000000000010 (
b00000000000000000000000000000010 $
b001 /
b00101000000000010000000000001010 1
b00000000000000000000000000001010 2
#30
0!
#35
1"
#37
b00000000000000000000000000000010 ,
b00000000000000000000000000000010 *
b00101000000000100000000000010100 )
b00000000000000000000000000010100 -
b001 0
b00101000000000010000000000001010 5
b00000000000000000000000000001010 6
#40
0"
#45
1!
#47
b00101000000000110000000000011001 '
b00000000000000000000000000000011 (
b00000000000000000000000000000011 $
b00101000000000100000000000010100 1
b00000000000000000000000000010100 2
#50
0!
#55
1"
#57
b00000000000000000000000000000011 ,
b00000000000000000000000000000011 *
b00101000000000110000000000011001 )
b00000000000000000000000000011001 -
b00101000000000100000000000010100 5
b00000000000000000000000000010100 6
#60
0"
#65
1!
#67
b00001100111001110111100000000000 '
b00000000000000000000000000000100 (
b00000000000000000000000000000100 $
b00101000000000110000000000011001 1
b00000000000000000000000000011001 2
#70
0!
#75
1"
#77
b00000000000000000000000000000111 +
b00000000000000000000000000000111 ,
b00000000000000000000000000000100 *
b00001100111001110111100000000000 )
b00000000000000000111100000000000 -
b000 .
b00101000000000110000000000011001 5
b00000000000000000000000000011001 6
#80
0"
#85
1!
#87
b00000000000000000000000000000101 (
b00000000000000000000000000000101 $
b000 /
b00001100111001110111100000000000 1
b00000000000000000000000000000111 2
#90
0!
#95
1"
#97
b00000000000000000000000000000101 *
b000 0
b00001100111001110111100000000000 5
b00000000000000000000000000000111 6
#100
0"
#105
1!
#107
b00000000001000100010000000000000 '
b00000000000000000000000000000110 (
b00000000000000000000000000000110 $
#110
0!
#115
1"
#117
b00000000000000000000000000001010 +
b00000000000000000000000000010100 ,
b00000000000000000000000000000110 *
b00000000001000100010000000000000 )
b00000000000000000010000000000000 -
#120
0"
#125
1!
#127
b00001100111001110111100000000000 '
b00000000000000000000000000000111 (
b00000000000000000000000000000111 $
b00000000001000100010000000000000 1
b00000000000000000000000000011110 2
#130
0!
#135
1"
#137
b00000000000000000000000000000111 +
b00000000000000000000000000000111 ,
b00000000000000000000000000000111 *
b00001100111001110111100000000000 )
b00000000000000000111100000000000 -
b00000000001000100010000000000000 5
b00000000000000000000000000011110 6
#140
0"
#145
1!
#147
b00000000100000110010100000000000 '
b00000000000000000000000000001000 (
b00000000000000000000000000001000 $
b00001100111001110111100000000000 1
b00000000000000000000000000000111 2
#150
0!
#155
1"
#157
b00000000000000000000000000011110 +
b00000000000000000000000000011001 ,
b00000000000000000000000000001000 *
b00000000100000110010100000000000 )
b00000000000000000010100000000000 -
b00001100111001110111100000000000 5
b00000000000000000000000000000111 6
#160
0"
#165
1!
#167
b11111100000000000000000000000000 '
b00000000000000000000000000001001 (
b00000000000000000000000000001001 $
b00000000100000110010100000000000 1
b00000000000000000000000000110111 2
#170
0!
#175
1"
b00000000000000000000000000000000 +
b00000000000000000000000000000000 ,
#177
b00000000000000000000000000001001 *
b11111100000000000000000000000000 )
b00000000000000000000000000000000 -
b101 .
b00000000100000110010100000000000 5
b00000000000000000000000000110111 6
#180
0"
#185
1!
#187
bxxxxxxxxxxxxxxxxxxxxxxxxxxxxxxxx '
b00000000000000000000000000001010 (
b00000000000000000000000000001010 $
b101 /
b11111100000000000000000000000000 1
#190
0!
#195
1"
#197
bxxxxxxxxxxxxxxxxxxxxxxxxxxxxxxxx +
bxxxxxxxxxxxxxxxxxxxxxxxxxxxxxxxx ,
b00000000000000000000000000001010 *
bxxxxxxxxxxxxxxxxxxxxxxxxxxxxxxxx )
bxxxxxxxxxxxxxxxxxxxxxxxxxxxxxxxx -
b101 0
b11111100000000000000000000000000 5
#200
0"
#205
1!
#207
b00000000000000000000000000001011 (
b00000000000000000000000000001011 $
bxxxxxxxxxxxxxxxxxxxxxxxxxxxxxxxx 1
1%
