MIPS32/mips32.v
//This module contains behavioral description verilog code
//for 5-stage pipelined MIPS32 RISC processor. 1-Bit regis-
//ster is used to halt processor(HALTD). 1-Bit register is
//used to evaluate branch conditions(TAKEN_BRANCH) and pre-
//vent any state changes.

module pipe_mips32(clk1,clk2);
  //Port declartion for module. Two-phased clock
  input clk1,clk2;

  //Registers for each stage  in pipeline process
  reg [31:0]PC,IF_ID_IR,IF_ID_NPC;
  reg [31:0]ID_EX_IR,ID_EX_NPC,ID_EX_A,ID_EX_B,ID_EX_Mem;
  reg [2:0]ID_EX_Type,EX_Mem_Type,Mem_WB_Type;
  reg [31:0]EX_Mem_IR,EX_Mem_ALUOut,EX_Mem_B;
  reg       EX_Mem_cond;
  reg [31:0]Mem_WB_IR,Mem_WB_ALUOut,Mem_WB_LMD;

  //Register bank(32x32) and 1024x32 memory
  reg [31:0]Reg[0:31];
  reg [31:0]Mem[0:1023];

  //ALU Instructions as parameters
  parameter ADD=6'b000000,SUB=6'b000001,AND=6'b000010,
            OR=6'b000011,SLT=6'b000100,MUL=6'b000101,
            HLT=6'b111111,LW=6'b001000,SW=6'b001001,
            ADDI=6'b001010,SUBI=6'b001011,SLTI=6'b001100,
            BNEQZ=6'b001101,BEQZ=6'b001110;
  //Special instructions as parameters
  parameter RR_ALU=3'b000,RM_ALU=3'b001,LOAD=3'b001,
            STORE=3'b011,BRANCH=3'b100,HALT=3'b101;

  //1-Bit flag for halting instructions
  reg HALTED;

  //1-Bit flag for branch instructions
  reg TAKEN_BRANCH;

  //Instruction Fetch Stage
  always@(posedge clk1)
  if(HALTED==0)
  begin
    if(((EX_Mem_IR[31:26]==BEQZ) && (EX_Mem_cond==1)) ||
        ((EX_Mem_IR[31:26]==BNEQZ) && (EX_Mem_cond==0)))
    begin
      IF_ID_IR <= #2 Mem[EX_Mem_ALUOut];
      TAKEN_BRANCH <= #2 1'b1;
      IF_ID_NPC <= #2 EX_Mem_ALUOut+1;
      PC <= #2 EX_Mem_ALUOut+1;
    end
    else
    begin
      IF_ID_IR <= #2 Mem[PC];
      IF_ID_NPC <= #2 PC+1;
      PC <= #2 PC+1;
    end
  end

  //Instruction Decode stage
  always@(posedge clk2)
  if(HALTED==0)
  begin
    //rs value from instruction
    if(IF_ID_IR[25:21]==5'b00000)
      ID_EX_A <= 0;
    else
      ID_EX_A <= #2 Reg[IF_ID_IR[25:21]];

    //rt value from instruction
    if(IF_ID_IR[20:16]==5'b00000)
      ID_EX_B <=0;
    else
      ID_EX_B <= #2 Reg[IF_ID_IR[20:16]];

    //forwarding remaining instructions
    ID_EX_NPC <= #2 IF_ID_NPC;
    ID_EX_IR <= #2 IF_ID_IR;
    ID_EX_Mem <= #2 {{16{IF_ID_IR[15]}},{IF_ID_IR[15:0]}};

    //Setting the execution command type
    case(IF_ID_IR[31:26])
      ADD,SUB,AND,OR,SLT,MUL: ID_EX_Type <= #2 RR_ALU;
      ADDI,SUBI,SLTI:         ID_EX_Type <= #2 RM_ALU;
      LW:                     ID_EX_Type <= #2 LOAD;
      SW:                     ID_EX_Type <= #2 STORE;
      BNEQZ,BEQZ:             ID_EX_Type <= #2 BRANCH;
      HLT:                    ID_EX_Type <= #2 HALT;
      default:                ID_EX_Type <= #2 HALT;
    endcase
  end

  //Execution stage
  always@(posedge clk1)
  if(HALTED==0)
  begin
    EX_Mem_Type <= #2 ID_EX_Type;
    EX_Mem_IR <= #2 ID_EX_Type;
    TAKEN_BRANCH <= #2 0;

    case(ID_EX_Type)
      //Register to Register type of instruction
      RR_ALU: begin
                case(ID_EX_IR[31:26])
                  ADD: EX_Mem_ALUOut <= #2 ID_EX_A + ID_EX_B;
                  SUB: EX_Mem_ALUOut <= #2 ID_EX_A - ID_EX_B;
                  MUL: EX_Mem_ALUOut <= #2 ID_EX_A * ID_EX_B;
                  AND: EX_Mem_ALUOut <= #2 ID_EX_A & ID_EX_B;
                  OR:  EX_Mem_ALUOut <= #2 ID_EX_A | ID_EX_B;
                  SLT: EX_Mem_ALUOut <= #2 ID_EX_A < ID_EX_B;
                  default: EX_Mem_ALUOut <= #2 32'hxxxxxxxx;
                endcase
              end

      //Register to Memory type of instruction
      RM_ALU: begin
                case(ID_EX_IR[31:26])
                  ADDI: EX_Mem_ALUOut <= #2 ID_EX_A + ID_EX_Mem;
                  SUBI: EX_Mem_ALUOut <= #2 ID_EX_A - ID_EX_Mem;
                  SLTI: EX_Mem_ALUOut <= #2 ID_EX_A < ID_EX_Mem;
                  default: EX_Mem_ALUOut <= #2 32'hxxxxxxxx;
                endcase
              end

      LOAD,STORE:
              begin
                EX_Mem_ALUOut <= #2 ID_EX_A + ID_EX_Mem;
                EX_Mem_B <= #2 ID_EX_B;
              end

      BRANCH: begin
                EX_Mem_ALUOut <= #2 ID_EX_NPC + ID_EX_Mem;
                EX_Mem_cond <= #2 (ID_EX_A==0);
              end
    endcase
  end  

  //Memory Access stage
  always@(posedge clk2)
  if(HALTED==0)
  begin
    Mem_WB_Type <= #2 EX_Mem_Type;
    Mem_WB_IR <= #2 EX_Mem_IR;

    //Memory access based on type of instruction
    case(EX_Mem_Type)
      RR_ALU,RM_ALU: Mem_WB_ALUOut <= #2 EX_Mem_ALUOut;
      LOAD: Mem_WB_ALUOut <= #2 Mem[EX_Mem_ALUOut];
      STORE: if(TAKEN_BRANCH==0)
               Mem[EX_Mem_ALUOut] <= #2 EX_Mem_B;
    endcase
  end

  //Write Back stage
  always@(posedge clk1)
  begin
    if(TAKEN_BRANCH==0)
    case(Mem_WB_Type)
      RR_ALU: Reg[Mem_WB_IR[15:11]] <= #2 Mem_WB_ALUOut;
      RM_ALU: Reg[Mem_WB_IR[20:16]] <= #2 Mem_WB_ALUOut;
      LOAD: Reg[Mem_WB_IR[20:16]] <= #2 Mem_WB_LMD;
      HALT: HALTED <= #2 1'b1;
    endcase
  end
endmodule

MIPS32/factorial_tb.v
//This testbench computes factorial of given number  in 200
//memory location and stores result in 198 memory location.
//Testbench illustrates branch instruction function and how
//negative numbers are stored in registers of processor.2's
//complement form is used to store negative numbers.
//Assembly language code for given test bench is as below:
//#########################################################
//ADDI R10,R0,200
//ADDI R2,R0,1
//LW R3,0(R10)
//Loop: MUL R2,R2,R3
//SUBI R3,R3,1
//BNEQZ R3,Loop
//SW R2, -2(R10)
//HLT
//#########################################################

module facttest_tb;
  reg clk1,clk2;
  integer k;

  pipe_mips32 fact(.clk1(clk1),.clk2(clk2));

  //procedural block to initialize clocks
  initial
  begin
    clk1=0;clk2=0;
    repeat(50)
    begin
      #5 clk1=1; #5 clk1=0;
      #5 clk2=1; #5 clk2=0; 
    end
  end

  //Stimuli for given assembly code
  initial
  begin
    for(k=0;k<31;k=k+1)
      fact.Reg[k]=k;

    //ADDI R10,R0,200
    fact.Mem[0]=32'h280a00c8;
    //ADDI R2,R0,1
    fact.Mem[1]=32'h28020001;
    //Dummy instruction to process pipeline
    fact.Mem[2]=32'h0e94a000;
    //LW R3,0(R10)
    fact.Mem[3]=32'h21430000;
    //Dummy instruction to process pipeline
    fact.Mem[4]=32'h0e94a000;
    //Loop: MUL R2,R2,R3
    fact.Mem[5]=32'h14431000;
    //SUBI R3,R3,1
    fact.Mem[6]=32'h2c630001;
    //Dummy instruction to process pipeline
    fact.Mem[7]=32'h0e94a000;
    //BNEQZ R3,Loop
    fact.Mem[8]=32'h3460fffc;
    //SW R2, -2(R10)
    fact.Mem[9]=32'h2542fffe;
    //HLT
    fact.Mem[10]=32'hfc000000;

   //Initializing 200th memory location
   fact.Mem[200]=7;

    //Initializing program counter and flags
    fact.PC=0;
    fact.TAKEN_BRANCH=0;
    fact.HALTED=0;

    #2000 $display("Mem[200]: %2d, Mem[198]: %6d",
                    fact.Mem[200],fact.Mem[198]);
  end

  initial
  begin
    $dumpfile("Factorial.vcd");
    $dumpvars(0,facttest_tb);
    $monitor("R2: %4d",fact.Reg[2]);
    #3000 $finish;
  end
endmodule

MIPS32/Factorial.vcd
$date
	Thu Jul 13 03:46:39 2023
$end

$version
	Synopsys VCS version Q-2020.03-SP1-1_Full64
$end

$timescale
	1s
$end

$comment Csum: 1 9fe93a3decbfbb04 $end


$scope module facttest_tb $end
$var reg 1 ! clk1 $end
$var reg 1 " clk2 $end
$var integer 32 # k $end

$scope module fact $end
$var reg 32 $ PC [31:0] $end
$var reg 1 % HALTED $end
$var reg 1 & TAKEN_BRANCH $end
$var wire 1 ! clk1 $end
$var wire 1 " clk2 $end
$var reg 32 ' IF_ID_IR [31:0] $end
$var reg 32 ( IF_ID_NPC [31:0] $end
$var reg 32 ) ID_EX_IR [31:0] $end
$var reg 32 * ID_EX_NPC [31:0] $end
$var reg 32 + ID_EX_A [31:0] $end
$var reg 32 , ID_EX_B [31:0] $end
$var reg 32 - ID_EX_Mem [31:0] $end
$var reg 3 . ID_EX_Type [2:0] $end
$var reg 3 / EX_Mem_Type [2:0] $end
$var reg 3 0 Mem_WB_Type [2:0] $end
$var reg 32 1 EX_Mem_IR [31:0] $end
$var reg 32 2 EX_Mem_ALUOut [31:0] $end
$var reg 32 3 EX_Mem_B [31:0] $end
$var reg 1 4 EX_Mem_cond $end
$var reg 32 5 Mem_WB_IR [31:0] $end
$var reg 32 6 Mem_WB_ALUOut [31:0] $end
$var reg 32 7 Mem_WB_LMD [31:0] $end
$upscope $end

$upscope $end

$enddefinitions $end

#0
$dumpvars
x4
0%
0&
0!
0"
bxxxxxxxxxxxxxxxxxxxxxxxxxxxxxxxx 2
bxxxxxxxxxxxxxxxxxxxxxxxxxxxxxxxx 3
bxxxxxxxxxxxxxxxxxxxxxxxxxxxxxxxx 1
bxxx /
bxxxxxxxxxxxxxxxxxxxxxxxxxxxxxxxx +
bxxxxxxxxxxxxxxxxxxxxxxxxxxxxxxxx ,
bxxxxxxxxxxxxxxxxxxxxxxxxxxxxxxxx )
bxxxxxxxxxxxxxxxxxxxxxxxxxxxxxxxx -
bxxxxxxxxxxxxxxxxxxxxxxxxxxxxxxxx *
bxxx .
bxxxxxxxxxxxxxxxxxxxxxxxxxxxxxxxx '
bxxxxxxxxxxxxxxxxxxxxxxxxxxxxxxxx (
bxxxxxxxxxxxxxxxxxxxxxxxxxxxxxxxx 6
bxxxxxxxxxxxxxxxxxxxxxxxxxxxxxxxx 5
bxxxxxxxxxxxxxxxxxxxxxxxxxxxxxxxx 7
bxxx 0
b00000000000000000000000000000000 $
b00000000000000000000000000011111 #
$end
#5
1!
#7
b00101000000010100000000011001000 '
b00000000000000000000000000000001 (
b00000000000000000000000000000001 $
#10
0!
#15
1"
b00000000000000000000000000000000 +
#17
b00000000000000000000000000001010 ,
b00000000000000000000000000000001 *
b00101000000010100000000011001000 )
b00000000000000000000000011001000 -
b001 .
#20
0"
#25
1!
#27
b00101000000000100000000000000001 '
b00000000000000000000000000000010 (
b00000000000000000000000000000010 $
b001 /
b00101000000010100000000011001000 1
b00000000000000000000000011001000 2
#30
0!
#35
1"
#37
b00000000000000000000000000000010 ,
b00000000000000000000000000000010 *
b00101000000000100000000000000001 )
b00000000000000000000000000000001 -
b001 0
b00101000000010100000000011001000 5
b00000000000000000000000011001000 6
#40
0"
#45
1!
#47
b00001110100101001010000000000000 '
b00000000000000000000000000000011 (
b00000000000000000000000000000011 $
b00101000000000100000000000000001 1
b00000000000000000000000000000001 2
#50
0!
#55
1"
#57
b00000000000000000000000000010100 +
b00000000000000000000000000010100 ,
b00000000000000000000000000000011 *
b00001110100101001010000000000000 )
b11111111111111111010000000000000 -
b000 .
b00101000000000100000000000000001 5
b00000000000000000000000000000001 6
#60
0"
#65
1!
#67
b00100001010000110000000000000000 '
b00000000000000000000000000000100 (
b00000000000000000000000000000100 $
b000 /
b00001110100101001010000000000000 1
b00000000000000000000000000010100 2
#70
0!
#75
1"
#77
b00000000000000000000000011001000 +
b00000000000000000000000000000011 ,
b00000000000000000000000000000100 *
b00100001010000110000000000000000 )
b00000000000000000000000000000000 -
b010 .
b000 0
b00001110100101001010000000000000 5
b00000000000000000000000000010100 6
#80
0"
#85
1!
#87
b00001110100101001010000000000000 '
b00000000000000000000000000000101 (
b00000000000000000000000000000101 $
b010 /
b00100001010000110000000000000000 1
b00000000000000000000000011001000 2
b00000000000000000000000000000011 3
#90
0!
#95
1"
#97
b00000000000000000000000000010100 +
b00000000000000000000000000010100 ,
b00000000000000000000000000000101 *
b00001110100101001010000000000000 )
b11111111111111111010000000000000 -
b000 .
b010 0
b00100001010000110000000000000000 5
b00000000000000000000000000000111 7
#100
0"
#105
1!
#107
b00010100010000110001000000000000 '
b00000000000000000000000000000110 (
b00000000000000000000000000000110 $
b000 /
b00001110100101001010000000000000 1
b00000000000000000000000000010100 2
#110
0!
#115
1"
#117
b00000000000000000000000000000001 +
b00000000000000000000000000000111 ,
b00000000000000000000000000000110 *
b00010100010000110001000000000000 )
b00000000000000000001000000000000 -
b000 0
b00001110100101001010000000000000 5
#120
0"
#125
1!
#127
b00101100011000110000000000000001 '
b00000000000000000000000000000111 (
b00000000000000000000000000000111 $
b00010100010000110001000000000000 1
b00000000000000000000000000000111 2
#130
0!
#135
1"
#137
b00000000000000000000000000000111 +
b00000000000000000000000000000111 *
b00101100011000110000000000000001 )
b00000000000000000000000000000001 -
b001 .
b00010100010000110001000000000000 5
b00000000000000000000000000000111 6
#140
0"
#145
1!
#147
b00001110100101001010000000000000 '
b00000000000000000000000000001000 (
b00000000000000000000000000001000 $
b001 /
b00101100011000110000000000000001 1
b00000000000000000000000000000110 2
#150
0!
#155
1"
#157
b00000000000000000000000000010100 +
b00000000000000000000000000010100 ,
b00000000000000000000000000001000 *
b00001110100101001010000000000000 )
b11111111111111111010000000000000 -
b000 .
b001 0
b00101100011000110000000000000001 5
b00000000000000000000000000000110 6
#160
0"
#165
1!
#167
b00110100011000001111111111111100 '
b00000000000000000000000000001001 (
b00000000000000000000000000001001 $
b000 /
b00001110100101001010000000000000 1
b00000000000000000000000000010100 2
#170
0!
#175
1"
b00000000000000000000000000000000 ,
#177
b00000000000000000000000000000110 +
b00000000000000000000000000001001 *
b00110100011000001111111111111100 )
b11111111111111111111111111111100 -
b100 .
b000 0
b00001110100101001010000000000000 5
b00000000000000000000000000010100 6
#180
0"
#185
1!
#187
b00100101010000101111111111111110 '
b00000000000000000000000000001010 (
b00000000000000000000000000001010 $
b100 /
b00110100011000001111111111111100 1
b00000000000000000000000000000101 2
04
#190
0!
#195
1"
#197
b00000000000000000000000011001000 +
b00000000000000000000000000000111 ,
b00000000000000000000000000001010 *
b00100101010000101111111111111110 )
b11111111111111111111111111111110 -
b011 .
b100 0
b00110100011000001111111111111100 5
#200
0"
#205
1!
#207
b00010100010000110001000000000000 '
1&
b00000000000000000000000000000110 (
b00000000000000000000000000000110 $
b011 /
b00100101010000101111111111111110 1
0&
b00000000000000000000000011000110 2
b00000000000000000000000000000111 3
#210
0!
#215
1"
#217
b00000000000000000000000000000111 +
b00000000000000000000000000000110 ,
b00000000000000000000000000000110 *
b00010100010000110001000000000000 )
b00000000000000000001000000000000 -
b000 .
b011 0
b00100101010000101111111111111110 5
#220
0"
#225
1!
#227
b00101100011000110000000000000001 '
b00000000000000000000000000000111 (
b00000000000000000000000000000111 $
b000 /
b00010100010000110001000000000000 1
b00000000000000000000000000101010 2
#230
0!
#235
1"
#237
b00000000000000000000000000000110 +
b00000000000000000000000000000111 *
b00101100011000110000000000000001 )
b00000000000000000000000000000001 -
b001 .
b000 0
b00010100010000110001000000000000 5
b00000000000000000000000000101010 6
#240
0"
#245
1!
#247
b00001110100101001010000000000000 '
b00000000000000000000000000001000 (
b00000000000000000000000000001000 $
b001 /
b00101100011000110000000000000001 1
b00000000000000000000000000000101 2
#250
0!
#255
1"
#257
b00000000000000000000000000010100 +
b00000000000000000000000000010100 ,
b00000000000000000000000000001000 *
b00001110100101001010000000000000 )
b11111111111111111010000000000000 -
b000 .
b001 0
b00101100011000110000000000000001 5
b00000000000000000000000000000101 6
#260
0"
#265
1!
#267
b00110100011000001111111111111100 '
b00000000000000000000000000001001 (
b00000000000000000000000000001001 $
b000 /
b00001110100101001010000000000000 1
b00000000000000000000000000010100 2
#270
0!
#275
1"
b00000000000000000000000000000000 ,
#277
b00000000000000000000000000000101 +
b00000000000000000000000000001001 *
b00110100011000001111111111111100 )
b11111111111111111111111111111100 -
b100 .
b000 0
b00001110100101001010000000000000 5
b00000000000000000000000000010100 6
#280
0"
#285
1!
#287
b00100101010000101111111111111110 '
b00000000000000000000000000001010 (
b00000000000000000000000000001010 $
b100 /
b00110100011000001111111111111100 1
b00000000000000000000000000000101 2
#290
0!
#295
1"
#297
b00000000000000000000000011001000 +
b00000000000000000000000000101010 ,
b00000000000000000000000000001010 *
b00100101010000101111111111111110 )
b11111111111111111111111111111110 -
b011 .
b100 0
b00110100011000001111111111111100 5
#300
0"
#305
1!
#307
b00010100010000110001000000000000 '
1&
b00000000000000000000000000000110 (
b00000000000000000000000000000110 $
b011 /
b00100101010000101111111111111110 1
0&
b00000000000000000000000011000110 2
b00000000000000000000000000101010 3
#310
0!
#315
1"
#317
b00000000000000000000000000101010 +
b00000000000000000000000000000101 ,
b00000000000000000000000000000110 *
b00010100010000110001000000000000 )
b00000000000000000001000000000000 -
b000 .
b011 0
b00100101010000101111111111111110 5
#320
0"
#325
1!
#327
b00101100011000110000000000000001 '
b00000000000000000000000000000111 (
b00000000000000000000000000000111 $
b000 /
b00010100010000110001000000000000 1
b00000000000000000000000011010010 2
#330
0!
#335
1"
#337
b00000000000000000000000000000101 +
b00000000000000000000000000000111 *
b00101100011000110000000000000001 )
b00000000000000000000000000000001 -
b001 .
b000 0
b00010100010000110001000000000000 5
b00000000000000000000000011010010 6
#340
0"
#345
1!
#347
b00001110100101001010000000000000 '
b00000000000000000000000000001000 (
b00000000000000000000000000001000 $
b001 /
b00101100011000110000000000000001 1
b00000000000000000000000000000100 2
#350
0!
#355
1"
#357
b00000000000000000000000000010100 +
b00000000000000000000000000010100 ,
b00000000000000000000000000001000 *
b00001110100101001010000000000000 )
b11111111111111111010000000000000 -
b000 .
b001 0
b00101100011000110000000000000001 5
b00000000000000000000000000000100 6
#360
0"
#365
1!
#367
b00110100011000001111111111111100 '
b00000000000000000000000000001001 (
b00000000000000000000000000001001 $
b000 /
b00001110100101001010000000000000 1
b00000000000000000000000000010100 2
#370
0!
#375
1"
b00000000000000000000000000000000 ,
#377
b00000000000000000000000000000100 +
b00000000000000000000000000001001 *
b00110100011000001111111111111100 )
b11111111111111111111111111111100 -
b100 .
b000 0
b00001110100101001010000000000000 5
b00000000000000000000000000010100 6
#380
0"
#385
1!
#387
b00100101010000101111111111111110 '
b00000000000000000000000000001010 (
b00000000000000000000000000001010 $
b100 /
b00110100011000001111111111111100 1
b00000000000000000000000000000101 2
#390
0!
#395
1"
#397
b00000000000000000000000011001000 +
b00000000000000000000000011010010 ,
b00000000000000000000000000001010 *
b00100101010000101111111111111110 )
b11111111111111111111111111111110 -
b011 .
b100 0
b00110100011000001111111111111100 5
#400
0"
#405
1!
#407
b00010100010000110001000000000000 '
1&
b00000000000000000000000000000110 (
b00000000000000000000000000000110 $
b011 /
b00100101010000101111111111111110 1
0&
b00000000000000000000000011000110 2
b00000000000000000000000011010010 3
#410
0!
#415
1"
#417
b00000000000000000000000011010010 +
b00000000000000000000000000000100 ,
b00000000000000000000000000000110 *
b00010100010000110001000000000000 )
b00000000000000000001000000000000 -
b000 .
b011 0
b00100101010000101111111111111110 5
#420
0"
#425
1!
#427
b00101100011000110000000000000001 '
b00000000000000000000000000000111 (
b00000000000000000000000000000111 $
b000 /
b00010100010000110001000000000000 1
b00000000000000000000001101001000 2
#430
0!
#435
1"
#437
b00000000000000000000000000000100 +
b00000000000000000000000000000111 *
b00101100011000110000000000000001 )
b00000000000000000000000000000001 -
b001 .
b000 0
b00010100010000110001000000000000 5
b00000000000000000000001101001000 6
#440
0"
#445
1!
#447
b00001110100101001010000000000000 '
b00000000000000000000000000001000 (
b00000000000000000000000000001000 $
b001 /
b00101100011000110000000000000001 1
b00000000000000000000000000000011 2
#450
0!
#455
1"
#457
b00000000000000000000000000010100 +
b00000000000000000000000000010100 ,
b00000000000000000000000000001000 *
b00001110100101001010000000000000 )
b11111111111111111010000000000000 -
b000 .
b001 0
b00101100011000110000000000000001 5
b00000000000000000000000000000011 6
#460
0"
#465
1!
#467
b00110100011000001111111111111100 '
b00000000000000000000000000001001 (
b00000000000000000000000000001001 $
b000 /
b00001110100101001010000000000000 1
b00000000000000000000000000010100 2
#470
0!
#475
1"
b00000000000000000000000000000000 ,
#477
b00000000000000000000000000000011 +
b00000000000000000000000000001001 *
b00110100011000001111111111111100 )
b11111111111111111111111111111100 -
b100 .
b000 0
b00001110100101001010000000000000 5
b00000000000000000000000000010100 6
#480
0"
#485
1!
#487
b00100101010000101111111111111110 '
b00000000000000000000000000001010 (
b00000000000000000000000000001010 $
b100 /
b00110100011000001111111111111100 1
b00000000000000000000000000000101 2
#490
0!
#495
1"
#497
b00000000000000000000000011001000 +
b00000000000000000000001101001000 ,
b00000000000000000000000000001010 *
b00100101010000101111111111111110 )
b11111111111111111111111111111110 -
b011 .
b100 0
b00110100011000001111111111111100 5
#500
0"
#505
1!
#507
b00010100010000110001000000000000 '
1&
b00000000000000000000000000000110 (
b00000000000000000000000000000110 $
b011 /
b00100101010000101111111111111110 1
0&
b00000000000000000000000011000110 2
b00000000000000000000001101001000 3
#510
0!
#515
1"
#517
b00000000000000000000001101001000 +
b00000000000000000000000000000011 ,
b00000000000000000000000000000110 *
b00010100010000110001000000000000 )
b00000000000000000001000000000000 -
b000 .
b011 0
b00100101010000101111111111111110 5
#520
0"
#525
1!
#527
b00101100011000110000000000000001 '
b00000000000000000000000000000111 (
b00000000000000000000000000000111 $
b000 /
b00010100010000110001000000000000 1
b00000000000000000000100111011000 2
#530
0!
#535
1"
#537
b00000000000000000000000000000011 +
b00000000000000000000000000000111 *
b00101100011000110000000000000001 )
b00000000000000000000000000000001 -
b001 .
b000 0
b00010100010000110001000000000000 5
b00000000000000000000100111011000 6
#540
0"
#545
1!
#547
b00001110100101001010000000000000 '
b00000000000000000000000000001000 (
b00000000000000000000000000001000 $
b001 /
b00101100011000110000000000000001 1
b00000000000000000000000000000010 2
#550
0!
#555
1"
#557
b00000000000000000000000000010100 +
b00000000000000000000000000010100 ,
b00000000000000000000000000001000 *
b00001110100101001010000000000000 )
b11111111111111111010000000000000 -
b000 .
b001 0
b00101100011000110000000000000001 5
b00000000000000000000000000000010 6
#560
0"
#565
1!
#567
b00110100011000001111111111111100 '
b00000000000000000000000000001001 (
b00000000000000000000000000001001 $
b000 /
b00001110100101001010000000000000 1
b00000000000000000000000000010100 2
#570
0!
#575
1"
b00000000000000000000000000000000 ,
#577
b00000000000000000000000000000010 +
b00000000000000000000000000001001 *
b00110100011000001111111111111100 )
b11111111111111111111111111111100 -
b100 .
b000 0
b00001110100101001010000000000000 5
b00000000000000000000000000010100 6
#580
0"
#585
1!
#587
b00100101010000101111111111111110 '
b00000000000000000000000000001010 (
b00000000000000000000000000001010 $
b100 /
b00110100011000001111111111111100 1
b00000000000000000000000000000101 2
#590
0!
#595
1"
#597
b00000000000000000000000011001000 +
b00000000000000000000100111011000 ,
b00000000000000000000000000001010 *
b00100101010000101111111111111110 )
b11111111111111111111111111111110 -
b011 .
b100 0
b00110100011000001111111111111100 5
#600
0"
#605
1!
#607
b00010100010000110001000000000000 '
1&
b00000000000000000000000000000110 (
b00000000000000000000000000000110 $
b011 /
b00100101010000101111111111111110 1
0&
b00000000000000000000000011000110 2
b00000000000000000000100111011000 3
#610
0!
#615
1"
#617
b00000000000000000000100111011000 +
b00000000000000000000000000000010 ,
b00000000000000000000000000000110 *
b00010100010000110001000000000000 )
b00000000000000000001000000000000 -
b000 .
b011 0
b00100101010000101111111111111110 5
#620
0"
#625
1!
#627
b00101100011000110000000000000001 '
b00000000000000000000000000000111 (
b00000000000000000000000000000111 $
b000 /
b00010100010000110001000000000000 1
b00000000000000000001001110110000 2
#630
0!
#635
1"
#637
b00000000000000000000000000000010 +
b00000000000000000000000000000111 *
b00101100011000110000000000000001 )
b00000000000000000000000000000001 -
b001 .
b000 0
b00010100010000110001000000000000 5
b00000000000000000001001110110000 6
#640
0"
#645
1!
#647
b00001110100101001010000000000000 '
b00000000000000000000000000001000 (
b00000000000000000000000000001000 $
b001 /
b00101100011000110000000000000001 1
b00000000000000000000000000000001 2
#650
0!
#655
1"
#657
b00000000000000000000000000010100 +
b00000000000000000000000000010100 ,
b00000000000000000000000000001000 *
b00001110100101001010000000000000 )
b11111111111111111010000000000000 -
b000 .
b001 0
b00101100011000110000000000000001 5
b00000000000000000000000000000001 6
#660
0"
#665
1!
#667
b00110100011000001111111111111100 '
b00000000000000000000000000001001 (
b00000000000000000000000000001001 $
b000 /
b00001110100101001010000000000000 1
b00000000000000000000000000010100 2
#670
0!
#675
1"
b00000000000000000000000000000000 ,
#677
b00000000000000000000000000000001 +
b00000000000000000000000000001001 *
b00110100011000001111111111111100 )
b11111111111111111111111111111100 -
b100 .
b000 0
b00001110100101001010000000000000 5
b00000000000000000000000000010100 6
#680
0"
#685
1!
#687
b00100101010000101111111111111110 '
b00000000000000000000000000001010 (
b00000000000000000000000000001010 $
b100 /
b00110100011000001111111111111100 1
b00000000000000000000000000000101 2
#690
0!
#695
1"
#697
b00000000000000000000000011001000 +
b00000000000000000001001110110000 ,
b00000000000000000000000000001010 *
b00100101010000101111111111111110 )
b11111111111111111111111111111110 -
b011 .
b100 0
b00110100011000001111111111111100 5
#700
0"
#705
1!
#707
b00010100010000110001000000000000 '
1&
b00000000000000000000000000000110 (
b00000000000000000000000000000110 $
b011 /
b00100101010000101111111111111110 1
0&
b00000000000000000000000011000110 2
b00000000000000000001001110110000 3
#710
0!
#715
1"
#717
b00000000000000000001001110110000 +
b00000000000000000000000000000001 ,
b00000000000000000000000000000110 *
b00010100010000110001000000000000 )
b00000000000000000001000000000000 -
b000 .
b011 0
b00100101010000101111111111111110 5
#720
0"
#725
1!
#727
b00101100011000110000000000000001 '
b00000000000000000000000000000111 (
b00000000000000000000000000000111 $
b000 /
b00010100010000110001000000000000 1
b00000000000000000001001110110000 2
#730
0!
#735
1"
#737
b00000000000000000000000000000001 +
b00000000000000000000000000000111 *
b00101100011000110000000000000001 )
b00000000000000000000000000000001 -
b001 .
b000 0
b00010100010000110001000000000000 5
b00000000000000000001001110110000 6
#740
0"
#745
1!
#747
b00001110100101001010000000000000 '
b00000000000000000000000000001000 (
b00000000000000000000000000001000 $
b001 /
b00101100011000110000000000000001 1
b00000000000000000000000000000000 2
#750
0!
#755
1"
#757
b00000000000000000000000000010100 +
b00000000000000000000000000010100 ,
b00000000000000000000000000001000 *
b00001110100101001010000000000000 )
b11111111111111111010000000000000 -
b000 .
b001 0
b00101100011000110000000000000001 5
b00000000000000000000000000000000 6
#760
0"
#765
1!
#767
b00110100011000001111111111111100 '
b00000000000000000000000000001001 (
b00000000000000000000000000001001 $
b000 /
b00001110100101001010000000000000 1
b00000000000000000000000000010100 2
#770
0!
#775
1"
b00000000000000000000000000000000 ,
#777
b00000000000000000000000000000000 +
b00000000000000000000000000001001 *
b00110100011000001111111111111100 )
b11111111111111111111111111111100 -
b100 .
b000 0
b00001110100101001010000000000000 5
b00000000000000000000000000010100 6
#780
0"
#785
1!
#787
b00100101010000101111111111111110 '
b00000000000000000000000000001010 (
b00000000000000000000000000001010 $
b100 /
b00110100011000001111111111111100 1
b00000000000000000000000000000101 2
14
#790
0!
#795
1"
#797
b00000000000000000000000011001000 +
b00000000000000000001001110110000 ,
b00000000000000000000000000001010 *
b00100101010000101111111111111110 )
b11111111111111111111111111111110 -
b011 .
b100 0
b00110100011000001111111111111100 5
#800
0"
#805
1!
#807
b11111100000000000000000000000000 '
b00000000000000000000000000001011 (
b00000000000000000000000000001011 $
b011 /
b00100101010000101111111111111110 1
b00000000000000000000000011000110 2
#810
0!
#815
1"
b00000000000000000000000000000000 +
b00000000000000000000000000000000 ,
#817
b00000000000000000000000000001011 *
b11111100000000000000000000000000 )
b00000000000000000000000000000000 -
b101 .
b011 0
b00100101010000101111111111111110 5
#820
0"
#825
1!
#827
bxxxxxxxxxxxxxxxxxxxxxxxxxxxxxxxx '
b00000000000000000000000000001100 (
b00000000000000000000000000001100 $
b101 /
b11111100000000000000000000000000 1
#830
0!
#835
1"
#837
bxxxxxxxxxxxxxxxxxxxxxxxxxxxxxxxx +
bxxxxxxxxxxxxxxxxxxxxxxxxxxxxxxxx ,
b00000000000000000000000000001100 *
bxxxxxxxxxxxxxxxxxxxxxxxxxxxxxxxx )
bxxxxxxxxxxxxxxxxxxxxxxxxxxxxxxxx -
b101 0
b11111100000000000000000000000000 5
#840
0"
#845
1!
#847
b00000000000000000000000000001101 (
b00000000000000000000000000001101 $
bxxxxxxxxxxxxxxxxxxxxxxxxxxxxxxxx 1
1%
