MIPS32/mips32.v
//This module contains behavioral description verilog code
//for 5-stage pipelined MIPS32 RISC processor. 1-Bit regis-
//ster is used to halt processor(HALTD). 1-Bit register is
//used to evaluate branch conditions(TAKEN_BRANCH) and pre-
//vent any state changes.

module pipe_mips32(clk1,clk2);
  //Port declartion for module. Two-phased clock
  input clk1,clk2;

  //Registers for each stage  in pipeline process
  reg [31:0]PC,IF_ID_IR,IF_ID_NPC;
  reg [31:0]ID_EX_IR,ID_EX_NPC,ID_EX_A,ID_EX_B,ID_EX_Mem;
  reg [2:0]ID_EX_Type,EX_Mem_Type,Mem_WB_Type;
  reg [31:0]EX_Mem_IR,EX_Mem_ALUOut,EX_Mem_B;
  reg       EX_Mem_cond;
  reg [31:0]Mem_WB_IR,Mem_WB_ALUOut,Mem_WB_LMD;

  //Register bank(32x32) and 1024x32 memory
  reg [31:0]Reg[0:31];
  reg [31:0]Mem[0:1023];

  //ALU Instructions as parameters
  parameter ADD=6'b000000,SUB=6'b000001,AND=6'b000010,
            OR=6'b000011,SLT=6'b000100,MUL=6'b000101,
            HLT=6'b111111,LW=6'b001000,SW=6'b001001,
            ADDI=6'b001010,SUBI=6'b001011,SLTI=6'b001100,
            BNEQZ=6'b001101,BEQZ=6'b001110;
  //Special instructions as parameters
  parameter RR_ALU=3'b000,RM_ALU=3'b001,LOAD=3'b001,
            STORE=3'b011,BRANCH=3'b100,HALT=3'b101;

  //1-Bit flag for halting instructions
  reg HALTED;

  //1-Bit flag for branch instructions
  reg TAKEN_BRANCH;

  //Instruction Fetch Stage
  always@(posedge clk1)
  if(HALTED==0)
  begin
    if(((EX_Mem_IR[31:26]==BEQZ) && (EX_Mem_cond==1)) ||
        ((EX_Mem_IR[31:26]==BNEQZ) && (EX_Mem_cond==0)))
    begin
      IF_ID_IR <= #2 Mem[EX_Mem_ALUOut];
      TAKEN_BRANCH <= #2 1'b1;
      IF_ID_NPC <= #2 EX_Mem_ALUOut+1;
      PC <= #2 EX_Mem_ALUOut+1;
    end
    else
    begin
      IF_ID_IR <= #2 Mem[PC];
      IF_ID_NPC <= #2 PC+1;
      PC <= #2 PC+1;
    end
  end

  //Instruction Decode stage
  always@(posedge clk2)
  if(HALTED==0)
  begin
    //rs value from instruction
    if(IF_ID_IR[25:21]==5'b00000)
      ID_EX_A <= 0;
    else
      ID_EX_A <= #2 Reg[IF_ID_IR[25:21]];

    //rt value from instruction
    if(IF_ID_IR[20:16]==5'b00000)
      ID_EX_B <=0;
    else
      ID_EX_B <= #2 Reg[IF_ID_IR[20:16]];

    //forwarding remaining instructions
    ID_EX_NPC <= #2 IF_ID_NPC;
    ID_EX_IR <= #2 IF_ID_IR;
    ID_EX_Mem <= #2 {{16{IF_ID_IR[15]}},{IF_ID_IR[15:0]}};

    //Setting the execution command type
    case(IF_ID_IR[31:26])
      ADD,SUB,AND,OR,SLT,MUL: ID_EX_Type <= #2 RR_ALU;
      ADDI,SUBI,SLTI:         ID_EX_Type <= #2 RM_ALU;
      LW:                     ID_EX_Type <= #2 LOAD;
      SW:                     ID_EX_Type <= #2 STORE;
      BNEQZ,BEQZ:             ID_EX_Type <= #2 BRANCH;
      HLT:                    ID_EX_Type <= #2 HALT;
      default:                ID_EX_Type <= #2 HALT;
    endcase
  end

  //Execution stage
  always@(posedge clk1)
  if(HALTED==0)
  begin
    EX_Mem_Type <= #2 ID_EX_Type;
    EX_Mem_IR <= #2 ID_EX_Type;
    TAKEN_BRANCH <= #2 0;

    case(ID_EX_Type)
      //Register to Register type of instruction
      RR_ALU: begin
                case(ID_EX_IR[31:26])
                  ADD: EX_Mem_ALUOut <= #2 ID_EX_A + ID_EX_B;
                  SUB: EX_Mem_ALUOut <= #2 ID_EX_A - ID_EX_B;
                  MUL: EX_Mem_ALUOut <= #2 ID_EX_A * ID_EX_B;
                  AND: EX_Mem_ALUOut <= #2 ID_EX_A & ID_EX_B;
                  OR:  EX_Mem_ALUOut <= #2 ID_EX_A | ID_EX_B;
                  SLT: EX_Mem_ALUOut <= #2 ID_EX_A < ID_EX_B;
                  default: EX_Mem_ALUOut <= #2 32'hxxxxxxxx;
                endcase
              end

      //Register to Memory type of instruction
      RM_ALU: begin
                case(ID_EX_IR[31:26])
                  ADDI: EX_Mem_ALUOut <= #2 ID_EX_A + ID_EX_Mem;
                  SUBI: EX_Mem_ALUOut <= #2 ID_EX_A - ID_EX_Mem;
                  SLTI: EX_Mem_ALUOut <= #2 ID_EX_A < ID_EX_Mem;
                  default: EX_Mem_ALUOut <= #2 32'hxxxxxxxx;
                endcase
              end

      LOAD,STORE:
              begin
                EX_Mem_ALUOut <= #2 ID_EX_A + ID_EX_Mem;
                EX_Mem_B <= #2 ID_EX_B;
              end

      BRANCH: begin
                EX_Mem_ALUOut <= #2 ID_EX_NPC + ID_EX_Mem;
                EX_Mem_cond <= #2 (ID_EX_A==0);
              end
    endcase
  end  

  //Memory Access stage
  always@(posedge clk2)
  if(HALTED==0)
  begin
    Mem_WB_Type <= #2 EX_Mem_Type;
    Mem_WB_IR <= #2 EX_Mem_IR;

    //Memory access based on type of instruction
    case(EX_Mem_Type)
      RR_ALU,RM_ALU: Mem_WB_ALUOut <= #2 EX_Mem_ALUOut;
      LOAD: Mem_WB_ALUOut <= #2 Mem[EX_Mem_ALUOut];
      STORE: if(TAKEN_BRANCH==0)
               Mem[EX_Mem_ALUOut] <= #2 EX_Mem_B;
    endcase
  end

  //Write Back stage
  always@(posedge clk1)
  begin
    if(TAKEN_BRANCH==0)
    case(Mem_WB_Type)
      RR_ALU: Reg[Mem_WB_IR[15:11]] <= #2 Mem_WB_ALUOut;
      RM_ALU: Reg[Mem_WB_IR[20:16]] <= #2 Mem_WB_ALUOut;
      LOAD: Reg[Mem_WB_IR[20:16]] <= #2 Mem_WB_LMD;
      HALT: HALTED <= #2 1'b1;
    endcase
  end
endmodule

MIPS32/loadadd_tb.v
//This example testbench loads words stored in memory loca-
//tion 120, adds 45 to it and stores result in memory loca-
//tion 121. We use R1 to initialize to memory location 121.
//Assembly language program is as below:
//#########################################################
//ADDI R1,R0,120
//LW R2,0(R1)
//ADDI R2,R2,45
//SW R2,1(R1)
//HTL
//#########################################################

module loadtest_tb;
  reg clk1,clk2;
  integer k;

  pipe_mips32 load(.clk1(clk1),.clk2(clk2));

  //procedure block to instantiate clocks
  initial
  begin
    clk1=0;clk2=0;
    repeat(50)
    begin
      #5 clk1=1; #5 clk1=0;
      #5 clk2=1; #5 clk2=0;
    end
  end

  //Stimulus for given program as machine code
  initial
  begin
    for(k=0;k<31;k=k+1)
      load.Reg[k]=k;

    //ADDI R1,R0,120
    load.Mem[0]=32'h28010078;
    //Dummy instruction to process pipeline
    load.Mem[1]=32'h0c631800;
    //LW R2,0(R1)
    load.Mem[2]=32'h20220000;
    //Dummy instruction to process pipeline
    load.Mem[3]=32'h0c631800;
    //ADDI R2,R2,45
    load.Mem[4]=32'h2842002d;
    //Dummy instruction to process pipeline
    load.Mem[5]=32'h0c631800;
    //SW R2,1(R1)
    load.Mem[6]=32'h24220001;
    //HLT
    load.Mem[7]=32'hfc000000;

    //Initializing 120th memory location
    load.Mem[120]=85;

    //Initializing program counter and other flags
    load.PC=0;
    load.HALTED=0;
    load.TAKEN_BRANCH=0;

    #500 $display("Mem[120]: %4d\nMem[121]: %4d",
                   load.Mem[120],load.Mem[121]);
  end

  initial
  begin
    $dumpfile("LoadandAdd.vcd");
    $dumpvars(0,loadtest_tb);
  end
endmodule

MIPS32/LoadandAdd.vcd
$date
	Wed Jul 12 03:47:10 2023
$end

$version
	Synopsys VCS version Q-2020.03-SP1-1_Full64
$end

$timescale
	1s
$end

$comment Csum: 1 eee6d5d74269c4a2 $end


$scope module loadtest_tb $end
$var reg 1 ! clk1 $end
$var reg 1 " clk2 $end
$var integer 32 # k $end

$scope module load $end
$var reg 32 $ PC [31:0] $end
$var reg 1 % HALTED $end
$var reg 1 & TAKEN_BRANCH $end
$var wire 1 ! clk1 $end
$var wire 1 " clk2 $end
$var reg 32 ' IF_ID_IR [31:0] $end
$var reg 32 ( IF_ID_NPC [31:0] $end
$var reg 32 ) ID_EX_IR [31:0] $end
$var reg 32 * ID_EX_NPC [31:0] $end
$var reg 32 + ID_EX_A [31:0] $end
$var reg 32 , ID_EX_B [31:0] $end
$var reg 32 - ID_EX_Mem [31:0] $end
$var reg 3 . ID_EX_Type [2:0] $end
$var reg 3 / EX_Mem_Type [2:0] $end
$var reg 3 0 Mem_WB_Type [2:0] $end
$var reg 32 1 EX_Mem_IR [31:0] $end
$var reg 32 2 EX_Mem_ALUOut [31:0] $end
$var reg 32 3 EX_Mem_B [31:0] $end
$var reg 1 4 EX_Mem_cond $end
$var reg 32 5 Mem_WB_IR [31:0] $end
$var reg 32 6 Mem_WB_ALUOut [31:0] $end
$var reg 32 7 Mem_WB_LMD [31:0] $end
$upscope $end

$upscope $end

$enddefinitions $end

#0
$dumpvars
x4
0%
0&
0!
0"
bxxxxxxxxxxxxxxxxxxxxxxxxxxxxxxxx 2
bxxxxxxxxxxxxxxxxxxxxxxxxxxxxxxxx 3
bxxxxxxxxxxxxxxxxxxxxxxxxxxxxxxxx 1
bxxx /
bxxxxxxxxxxxxxxxxxxxxxxxxxxxxxxxx +
bxxxxxxxxxxxxxxxxxxxxxxxxxxxxxxxx ,
bxxxxxxxxxxxxxxxxxxxxxxxxxxxxxxxx )
bxxxxxxxxxxxxxxxxxxxxxxxxxxxxxxxx -
bxxxxxxxxxxxxxxxxxxxxxxxxxxxxxxxx *
bxxx .
bxxxxxxxxxxxxxxxxxxxxxxxxxxxxxxxx '
bxxxxxxxxxxxxxxxxxxxxxxxxxxxxxxxx (
bxxxxxxxxxxxxxxxxxxxxxxxxxxxxxxxx 6
bxxxxxxxxxxxxxxxxxxxxxxxxxxxxxxxx 5
bxxxxxxxxxxxxxxxxxxxxxxxxxxxxxxxx 7
bxxx 0
b00000000000000000000000000000000 $
b00000000000000000000000000011111 #
$end
#5
1!
#7
b00101000000000010000000001111000 '
b00000000000000000000000000000001 (
b00000000000000000000000000000001 $
#10
0!
#15
1"
b00000000000000000000000000000000 +
#17
b00000000000000000000000000000001 ,
b00000000000000000000000000000001 *
b00101000000000010000000001111000 )
b00000000000000000000000001111000 -
b001 .
#20
0"
#25
1!
#27
b00001100011000110001100000000000 '
b00000000000000000000000000000010 (
b00000000000000000000000000000010 $
b001 /
b00101000000000010000000001111000 1
b00000000000000000000000001111000 2
#30
0!
#35
1"
#37
b00000000000000000000000000000011 +
b00000000000000000000000000000011 ,
b00000000000000000000000000000010 *
b00001100011000110001100000000000 )
b00000000000000000001100000000000 -
b000 .
b001 0
b00101000000000010000000001111000 5
b00000000000000000000000001111000 6
#40
0"
#45
1!
#47
b00100000001000100000000000000000 '
b00000000000000000000000000000011 (
b00000000000000000000000000000011 $
b000 /
b00001100011000110001100000000000 1
b00000000000000000000000000000011 2
#50
0!
#55
1"
#57
b00000000000000000000000001111000 +
b00000000000000000000000000000010 ,
b00000000000000000000000000000011 *
b00100000001000100000000000000000 )
b00000000000000000000000000000000 -
b010 .
b000 0
b00001100011000110001100000000000 5
b00000000000000000000000000000011 6
#60
0"
#65
1!
#67
b00001100011000110001100000000000 '
b00000000000000000000000000000100 (
b00000000000000000000000000000100 $
b010 /
b00100000001000100000000000000000 1
b00000000000000000000000001111000 2
b00000000000000000000000000000010 3
#70
0!
#75
1"
#77
b00000000000000000000000000000011 +
b00000000000000000000000000000011 ,
b00000000000000000000000000000100 *
b00001100011000110001100000000000 )
b00000000000000000001100000000000 -
b000 .
b010 0
b00100000001000100000000000000000 5
b00000000000000000000000001010101 7
#80
0"
#85
1!
#87
b00101000010000100000000000101101 '
b00000000000000000000000000000101 (
b00000000000000000000000000000101 $
b000 /
b00001100011000110001100000000000 1
b00000000000000000000000000000011 2
#90
0!
#95
1"
#97
b00000000000000000000000001010101 +
b00000000000000000000000001010101 ,
b00000000000000000000000000000101 *
b00101000010000100000000000101101 )
b00000000000000000000000000101101 -
b001 .
b000 0
b00001100011000110001100000000000 5
#100
0"
#105
1!
#107
b00001100011000110001100000000000 '
b00000000000000000000000000000110 (
b00000000000000000000000000000110 $
b001 /
b00101000010000100000000000101101 1
b00000000000000000000000010000010 2
#110
0!
#115
1"
#117
b00000000000000000000000000000011 +
b00000000000000000000000000000011 ,
b00000000000000000000000000000110 *
b00001100011000110001100000000000 )
b00000000000000000001100000000000 -
b000 .
b001 0
b00101000010000100000000000101101 5
b00000000000000000000000010000010 6
#120
0"
#125
1!
#127
b00100100001000100000000000000001 '
b00000000000000000000000000000111 (
b00000000000000000000000000000111 $
b000 /
b00001100011000110001100000000000 1
b00000000000000000000000000000011 2
#130
0!
#135
1"
#137
b00000000000000000000000001111000 +
b00000000000000000000000010000010 ,
b00000000000000000000000000000111 *
b00100100001000100000000000000001 )
b00000000000000000000000000000001 -
b011 .
b000 0
b00001100011000110001100000000000 5
b00000000000000000000000000000011 6
#140
0"
#145
1!
#147
b11111100000000000000000000000000 '
b00000000000000000000000000001000 (
b00000000000000000000000000001000 $
b011 /
b00100100001000100000000000000001 1
b00000000000000000000000001111001 2
b00000000000000000000000010000010 3
#150
0!
#155
1"
b00000000000000000000000000000000 +
b00000000000000000000000000000000 ,
#157
b00000000000000000000000000001000 *
b11111100000000000000000000000000 )
b00000000000000000000000000000000 -
b101 .
b011 0
b00100100001000100000000000000001 5
#160
0"
#165
1!
#167
bxxxxxxxxxxxxxxxxxxxxxxxxxxxxxxxx '
b00000000000000000000000000001001 (
b00000000000000000000000000001001 $
b101 /
b11111100000000000000000000000000 1
#170
0!
#175
1"
#177
bxxxxxxxxxxxxxxxxxxxxxxxxxxxxxxxx +
bxxxxxxxxxxxxxxxxxxxxxxxxxxxxxxxx ,
b00000000000000000000000000001001 *
bxxxxxxxxxxxxxxxxxxxxxxxxxxxxxxxx )
bxxxxxxxxxxxxxxxxxxxxxxxxxxxxxxxx -
b101 0
b11111100000000000000000000000000 5
#180
0"
#185
1!
#187
b00000000000000000000000000001010 (
b00000000000000000000000000001010 $
bxxxxxxxxxxxxxxxxxxxxxxxxxxxxxxxx 1
1%
